outlooktools/__about__.py
outlooktools/__init__.py
outlooktools/__main__.py
outlooktools/outlook_connection.py
outlooktools/cli/__init__.py
outlooktools-0.1.1.dist-info/METADATA
outlooktools-0.1.1.dist-info/WHEEL
outlooktools-0.1.1.dist-info/entry_points.txt
outlooktools-0.1.1.dist-info/licenses/LICENSE.txt
outlooktools-0.1.1.dist-info/RECORD
