Metadata-Version: 2.1
Name: outlooktools
Version: 0.1.1
Summary: Windows CLI to automate Outlook tasks
Project-URL: Documentation, https://github.com/richmr/outlooktools#readme
Project-URL: Issues, https://github.com/richmr/outlooktools/issues
Project-URL: Source, https://github.com/richmr/outlooktools
Author-email: richmr <richmr@users.noreply.github.com>
License-Expression: MIT
License-File: LICENSE.txt
Classifier: Development Status :: 4 - Beta
Classifier: Programming Language :: Python
Classifier: Programming Language :: Python :: 3.7
Classifier: Programming Language :: Python :: 3.8
Classifier: Programming Language :: Python :: 3.9
Classifier: Programming Language :: Python :: 3.10
Classifier: Programming Language :: Python :: 3.11
Classifier: Programming Language :: Python :: Implementation :: CPython
Classifier: Programming Language :: Python :: Implementation :: PyPy
Requires-Python: >=3.7
Requires-Dist: pywin32
Requires-Dist: typer[all]
